reportlab-stubs/graphics/__init__.pyi
reportlab-stubs/graphics/_renderPM.pyi
reportlab-stubs/graphics/renderPDF.pyi
reportlab-stubs/graphics/renderPM.pyi
reportlab-stubs/graphics/renderPS.pyi
reportlab-stubs/graphics/renderSVG.pyi
reportlab-stubs/graphics/renderbase.pyi
reportlab-stubs/graphics/shapes.pyi
reportlab-stubs/graphics/testdrawings.pyi
reportlab-stubs/graphics/testshapes.pyi
reportlab-stubs/graphics/transform.pyi
reportlab-stubs/graphics/utils.pyi
reportlab-stubs/graphics/widgetbase.pyi
reportlab-stubs/lib/PyFontify.pyi
reportlab-stubs/lib/__init__.pyi
reportlab-stubs/lib/_rl_accel.pyi
reportlab-stubs/lib/abag.pyi
reportlab-stubs/lib/arciv.pyi
reportlab-stubs/lib/attrmap.pyi
reportlab-stubs/lib/boxstuff.pyi
reportlab-stubs/lib/codecharts.pyi
reportlab-stubs/lib/colors.pyi
reportlab-stubs/lib/corp.pyi
reportlab-stubs/lib/enums.pyi
reportlab-stubs/lib/extformat.pyi
reportlab-stubs/lib/fontfinder.pyi
reportlab-stubs/lib/fonts.pyi
reportlab-stubs/lib/formatters.pyi
reportlab-stubs/lib/geomutils.pyi
reportlab-stubs/lib/logger.pyi
reportlab-stubs/lib/normalDate.pyi
reportlab-stubs/lib/pagesizes.pyi
reportlab-stubs/lib/pdfencrypt.pyi
reportlab-stubs/lib/pygments2xpre.pyi
reportlab-stubs/lib/randomtext.pyi
reportlab-stubs/lib/rl_accel.pyi
reportlab-stubs/lib/rl_safe_eval.pyi
reportlab-stubs/lib/rltempfile.pyi
reportlab-stubs/lib/rparsexml.pyi
reportlab-stubs/lib/sequencer.pyi
reportlab-stubs/lib/styles.pyi
reportlab-stubs/lib/testutils.pyi
reportlab-stubs/lib/textsplit.pyi
reportlab-stubs/lib/units.pyi
reportlab-stubs/lib/utils.pyi
reportlab-stubs/lib/validators.pyi
reportlab-stubs/lib/yaml.pyi
reportlab-stubs/pdfbase/__init__.pyi
reportlab-stubs/pdfbase/_can_cmap_data.pyi
reportlab-stubs/pdfbase/_cidfontdata.pyi
reportlab-stubs/pdfbase/_fontdata.pyi
reportlab-stubs/pdfbase/_fontdata_enc_macexpert.pyi
reportlab-stubs/pdfbase/_fontdata_enc_macroman.pyi
reportlab-stubs/pdfbase/_fontdata_enc_pdfdoc.pyi
reportlab-stubs/pdfbase/_fontdata_enc_standard.pyi
reportlab_stubs-3.6.9.post0.dist-info/METADATA
reportlab_stubs-3.6.9.post0.dist-info/WHEEL
reportlab_stubs-3.6.9.post0.dist-info/top_level.txt
reportlab_stubs-3.6.9.post0.dist-info/RECORD
