Metadata-Version: 2.1
Name: reportlab-stubs
Version: 3.6.9.post0
Summary: Typing stubs for ReportLab
Home-page: https://github.com/eggplants/reportlab-stubs
Author: eggplants
Author-email: w10776e8w@yahoo.co.jp
License: BSD License
Platform: UNKNOWN
Classifier: Intended Audience :: Developers
Classifier: Programming Language :: Python
Requires-Dist: reportlab
Provides-Extra: dev
Requires-Dist: black ; extra == 'dev'
Requires-Dist: flake8 ; extra == 'dev'
Requires-Dist: flake8-black ; extra == 'dev'
Requires-Dist: flake8-pyi ; extra == 'dev'
Requires-Dist: mypy ; extra == 'dev'
Requires-Dist: setuptools ; extra == 'dev'
Requires-Dist: types-setuptools ; extra == 'dev'
Requires-Dist: wheel ; extra == 'dev'
